{"mean":{"confidence_interval":{"confidence_level":0.95,"lower_bound":239960180.897,"upper_bound":243247951.041},"point_estimate":241510422.7,"standard_error":840824.2207161847},"median":{"confidence_interval":{"confidence_level":0.95,"lower_bound":239636938.0,"upper_bound":241752474.0},"point_estimate":241103660.5,"standard_error":551417.3919622753},"median_abs_dev":{"confidence_interval":{"confidence_level":0.95,"lower_bound":2133650.3936201334,"upper_bound":6215449.013453722},"point_estimate":4175526.3662695885,"standard_error":1051200.665784236},"slope":null,"std_dev":{"confidence_interval":{"confidence_level":0.95,"lower_bound":4066433.5505600404,"upper_bound":7786339.924081239},"point_estimate":6007816.016393891,"standard_error":966800.3021640668}}