{"mean":{"confidence_interval":{"confidence_level":0.95,"lower_bound":72050.30629911774,"upper_bound":72969.00844189938},"point_estimate":72409.26325374519,"standard_error":242.62474787446996},"median":{"confidence_interval":{"confidence_level":0.95,"lower_bound":71906.07575757576,"upper_bound":72189.76320773525},"point_estimate":72067.63867845119,"standard_error":73.48116317415219},"median_abs_dev":{"confidence_interval":{"confidence_level":0.95,"lower_bound":227.40426095854838,"upper_bound":482.5093306873738},"point_estimate":331.72488690743245,"standard_error":67.39582425396048},"slope":{"confidence_interval":{"confidence_level":0.95,"lower_bound":72098.26976306159,"upper_bound":74095.20618259624},"point_estimate":72900.61854503097,"standard_error":533.931207453669},"std_dev":{"confidence_interval":{"confidence_level":0.95,"lower_bound":310.8446674150035,"upper_bound":2810.5506297854627},"point_estimate":1729.8149745506923,"standard_error":748.4129561624006}}