{"mean":{"confidence_interval":{"confidence_level":0.95,"lower_bound":4697666.223626401,"upper_bound":4939699.698918128},"point_estimate":4810083.250202842,"standard_error":62065.1535211525},"median":{"confidence_interval":{"confidence_level":0.95,"lower_bound":4621754.544642857,"upper_bound":4951005.66875},"point_estimate":4693728.267857143,"standard_error":77947.71468961585},"median_abs_dev":{"confidence_interval":{"confidence_level":0.95,"lower_bound":61631.7426808183,"upper_bound":364403.62530701235},"point_estimate":155066.5909020177,"standard_error":85088.4756134758},"slope":{"confidence_interval":{"confidence_level":0.95,"lower_bound":4711141.717577553,"upper_bound":5012812.780791486},"point_estimate":4859333.71271777,"standard_error":77246.78411036682},"std_dev":{"confidence_interval":{"confidence_level":0.95,"lower_bound":163999.74424558118,"upper_bound":384600.08728160005},"point_estimate":284707.69209827884,"standard_error":60074.75994399531}}